{
  "TotalProcessed": 3,
  "LastCreated": "2025-09-13T10:55:58Z",
  "MatchingPosts": [
    {
      "Created": "2025-09-13T10:24:56Z",
      "Title": "rsa.ImportFromPem(privateKeyString) throws strange error in .net 6.0 restapi",
      "Tags": [
        "base64",
        "asp.net-core-webapi",
        "rsa",
        ".net-6.0",
        "private-key"
      ],
      "Url": "https://stackoverflow.com/questions/79763658/rsa-importfrompemprivatekeystring-throws-strange-error-in-net-6-0-restapi"
    },
    {
      "Created": "2025-09-13T10:36:30Z",
      "Title": "Access child components (getters) from a Slint root component",
      "Tags": [
        "rust",
        "slint"
      ],
      "Url": "https://stackoverflow.com/questions/79763663/access-child-components-getters-from-a-slint-root-component"
    },
    {
      "Created": "2025-09-13T10:55:58Z",
      "Title": "session.get not getting corrected file on remote server/local server",
      "Tags": [
        "python",
        "django",
        "session",
        "python-requests",
        "cloudflare"
      ],
      "Url": "https://stackoverflow.com/questions/79763668/session-get-not-getting-corrected-file-on-remote-server-local-server"
    }
  ]
}
