{
  "TotalProcessed": 2,
  "LastCreated": "2025-07-13T04:00:15Z",
  "MatchingPosts": [
    {
      "Created": "2025-07-13T03:59:14Z",
      "Title": "Asynchronously and quickly make many API requests in JavaScript while handling or preventing 429 CORS error messages",
      "Tags": [
        "javascript",
        "cors",
        "fetch-api"
      ],
      "Url": "https://stackoverflow.com/questions/79699722/asynchronously-and-quickly-make-many-api-requests-in-javascript-while-handling-o"
    },
    {
      "Created": "2025-07-13T04:00:15Z",
      "Title": "Sagemath plotting cannot let me change y position of my title",
      "Tags": [
        "sage"
      ],
      "Url": "https://stackoverflow.com/questions/79699723/sagemath-plotting-cannot-let-me-change-y-position-of-my-title"
    }
  ]
}
