{
  "TotalProcessed": 3,
  "LastCreated": "2025-09-23T08:05:24Z",
  "MatchingPosts": [
    {
      "Created": "2025-09-23T07:38:21Z",
      "Title": "MCU 8051 naming registers in assembly language",
      "Tags": [
        "8051"
      ],
      "Url": "https://stackoverflow.com/questions/79772328/mcu-8051-naming-registers-in-assembly-language"
    },
    {
      "Created": "2025-09-23T08:03:55Z",
      "Title": "Real time voice communication using raspberry pi: Error in decoding ffmpeg data at receiver side",
      "Tags": [
        "python-3.x",
        "ffmpeg",
        "raspberry-pi",
        "ffmpeg-python",
        "pyffmpeg"
      ],
      "Url": "https://stackoverflow.com/questions/79772351/real-time-voice-communication-using-raspberry-pi-error-in-decoding-ffmpeg-data"
    },
    {
      "Created": "2025-09-23T08:05:24Z",
      "Title": "VS Code C\u002B\u002B Formatting - Leave blank line before closing bracket",
      "Tags": [
        "visual-studio-code",
        "clang-format"
      ],
      "Url": "https://stackoverflow.com/questions/79772354/vs-code-c-formatting-leave-blank-line-before-closing-bracket"
    }
  ]
}
